writerai/__init__.py
writerai/_base_client.py
writerai/_client.py
writerai/_compat.py
writerai/_constants.py
writerai/_exceptions.py
writerai/_files.py
writerai/_models.py
writerai/_qs.py
writerai/_resource.py
writerai/_response.py
writerai/_streaming.py
writerai/_types.py
writerai/_version.py
writerai/pagination.py
writerai/py.typed
writerai/_utils/__init__.py
writerai/_utils/_compat.py
writerai/_utils/_datetime_parse.py
writerai/_utils/_logs.py
writerai/_utils/_proxy.py
writerai/_utils/_reflection.py
writerai/_utils/_resources_proxy.py
writerai/_utils/_streams.py
writerai/_utils/_sync.py
writerai/_utils/_transform.py
writerai/_utils/_typing.py
writerai/_utils/_utils.py
writerai/lib/.keep
writerai/lib/__init__.py
writerai/lib/_pydantic.py
writerai/lib/_tools.py
writerai/lib/_parsing/__init__.py
writerai/lib/_parsing/_completions.py
writerai/lib/streaming/__init__.py
writerai/lib/streaming/_deltas.py
writerai/lib/streaming/chat/__init__.py
writerai/lib/streaming/chat/_completions.py
writerai/lib/streaming/chat/_events.py
writerai/lib/streaming/chat/_types.py
writerai/resources/__init__.py
writerai/resources/applications.py
writerai/resources/chat.py
writerai/resources/completions.py
writerai/resources/files.py
writerai/resources/graphs.py
writerai/resources/models.py
writerai/resources/translation.py
writerai/resources/vision.py
writerai/resources/applications/__init__.py
writerai/resources/applications/applications.py
writerai/resources/applications/graphs.py
writerai/resources/applications/jobs.py
writerai/resources/tools/__init__.py
writerai/resources/tools/comprehend.py
writerai/resources/tools/tools.py
writerai/types/__init__.py
writerai/types/application_generate_content_chunk.py
writerai/types/application_generate_content_params.py
writerai/types/application_generate_content_response.py
writerai/types/application_list_params.py
writerai/types/application_list_response.py
writerai/types/application_retrieve_response.py
writerai/types/chat_chat_params.py
writer_sdk-2.3.2.dist-info/METADATA
writer_sdk-2.3.2.dist-info/WHEEL
writer_sdk-2.3.2.dist-info/licenses/LICENSE
writer_sdk-2.3.2.dist-info/RECORD
